Compiled from "TestPaths.java"
public class TestPaths {
  public TestPaths();
    Code:
       0: aload_0
       1: invokespecial #1                  // Method java/lang/Object."<init>":()V
       4: return

  public static void main(java.lang.String[]);
    Code:
       0: getstatic     #2                  // Field java/lang/System.out:Ljava/io/PrintStream;
       3: ldc           #3                  // String !!!!!!!!!!!!!!! Start Testing!
       5: invokevirtual #4                  // Method java/io/PrintStream.println:(Ljava/lang/String;)V
       8: new           #5                  // class TestPaths
      11: dup
      12: invokespecial #6                  // Method "<init>":()V
      15: iconst_0
      16: iconst_0
      17: invokevirtual #7                  // Method testMe3:(II)V
      20: return

  public void testMe3(int, int);
    Code:
       0: bipush        11
       2: istore_3
       3: bipush        12
       5: istore        4
       7: iload_1
       8: ifge          14
      11: iconst_m1
      12: istore_3
      13: return
      14: iload_1
      15: ifne          23
      18: iconst_0
      19: istore_3
      20: goto          25
      23: iconst_1
      24: istore_3
      25: iload_2
      26: ifge          35
      29: iconst_m1
      30: istore        4
      32: goto          46
      35: iload_2
      36: ifne          43
      39: iconst_0
      40: istore        4
      42: return
      43: iconst_1
      44: istore        4
      46: iload_3
      47: iconst_m1
      48: if_icmpne     62
      51: getstatic     #2                  // Field java/lang/System.out:Ljava/io/PrintStream;
      54: ldc           #8                  // String a = -1
      56: invokevirtual #4                  // Method java/io/PrintStream.println:(Ljava/lang/String;)V
      59: goto          86
      62: iload_3
      63: iconst_1
      64: if_icmpne     78
      67: getstatic     #2                  // Field java/lang/System.out:Ljava/io/PrintStream;
      70: ldc           #9                  // String a = 1
      72: invokevirtual #4                  // Method java/io/PrintStream.println:(Ljava/lang/String;)V
      75: goto          86
      78: getstatic     #2                  // Field java/lang/System.out:Ljava/io/PrintStream;
      81: ldc           #10                 // String a != 1 && a != -1
      83: invokevirtual #4                  // Method java/io/PrintStream.println:(Ljava/lang/String;)V
      86: iload         4
      88: iconst_m1
      89: if_icmpne     103
      92: getstatic     #2                  // Field java/lang/System.out:Ljava/io/PrintStream;
      95: ldc           #11                 // String b = -1
      97: invokevirtual #4                  // Method java/io/PrintStream.println:(Ljava/lang/String;)V
     100: goto          128
     103: iload         4
     105: iconst_1
     106: if_icmpne     120
     109: getstatic     #2                  // Field java/lang/System.out:Ljava/io/PrintStream;
     112: ldc           #12                 // String b = 1
     114: invokevirtual #4                  // Method java/io/PrintStream.println:(Ljava/lang/String;)V
     117: goto          128
     120: getstatic     #2                  // Field java/lang/System.out:Ljava/io/PrintStream;
     123: ldc           #13                 // String b != 1 && b != 1
     125: invokevirtual #4                  // Method java/io/PrintStream.println:(Ljava/lang/String;)V
     128: getstatic     #2                  // Field java/lang/System.out:Ljava/io/PrintStream;
     131: ldc           #14                 // String -x-x-x-x-
     133: invokevirtual #4                  // Method java/io/PrintStream.println:(Ljava/lang/String;)V
     136: return

  public static void testMe(int, boolean);
    Code:
       0: getstatic     #2                  // Field java/lang/System.out:Ljava/io/PrintStream;
       3: new           #15                 // class java/lang/StringBuilder
       6: dup
       7: invokespecial #16                 // Method java/lang/StringBuilder."<init>":()V
      10: ldc           #17                 // String x =
      12: invokevirtual #18                 // Method java/lang/StringBuilder.append:(Ljava/lang/String;)Ljava/lang/StringBuilder;
      15: iload_0
      16: invokevirtual #19                 // Method java/lang/StringBuilder.append:(I)Ljava/lang/StringBuilder;
      19: invokevirtual #20                 // Method java/lang/StringBuilder.toString:()Ljava/lang/String;
      22: invokevirtual #4                  // Method java/io/PrintStream.println:(Ljava/lang/String;)V
      25: iconst_0
      26: istore_2
      27: iload_0
      28: sipush        1200
      31: if_icmpgt     36
      34: iconst_m1
      35: istore_2
      36: iload_0
      37: sipush        1200
      40: if_icmplt     45
      43: iconst_1
      44: istore_2
      45: return

  public void testMe2(int, boolean);
    Code:
       0: getstatic     #2                  // Field java/lang/System.out:Ljava/io/PrintStream;
       3: ldc           #21                 // String !!!!!!!!!!!!!!! First step!
       5: invokevirtual #4                  // Method java/io/PrintStream.println:(Ljava/lang/String;)V
       8: iload_2
       9: ifeq          45
      12: iload_1
      13: sipush        1200
      16: if_icmpgt     27
      19: getstatic     #2                  // Field java/lang/System.out:Ljava/io/PrintStream;
      22: ldc           #22                 // String   <= 1200
      24: invokevirtual #4                  // Method java/io/PrintStream.println:(Ljava/lang/String;)V
      27: iload_1
      28: sipush        1200
      31: if_icmplt     53
      34: getstatic     #2                  // Field java/lang/System.out:Ljava/io/PrintStream;
      37: ldc           #23                 // String   >= 1200
      39: invokevirtual #4                  // Method java/io/PrintStream.println:(Ljava/lang/String;)V
      42: goto          53
      45: getstatic     #2                  // Field java/lang/System.out:Ljava/io/PrintStream;
      48: ldc           #24                 // String   b is false
      50: invokevirtual #4                  // Method java/io/PrintStream.println:(Ljava/lang/String;)V
      53: return
}
