Compiled from "VeritestingPerf.java"
public class VeritestingPerf {
  public VeritestingPerf();
    descriptor: ()V
    Code:
       0: aload_0
       1: invokespecial #1                  // Method java/lang/Object."<init>":()V
       4: return

  public static void main(java.lang.String[]);
    descriptor: ([Ljava/lang/String;)V
    Code:
       0: new           #2                  // class VeritestingPerf
       3: dup
       4: invokespecial #3                  // Method "<init>":()V
       7: iconst_0
       8: invokevirtual #4                  // Method oneBranch:(I)I
      11: pop
      12: return

  public void testMe4(int[], int);
    descriptor: ([II)V
    Code:
       0: iconst_0
       1: istore_3
       2: iconst_0
       3: istore        4
       5: iload         4
       7: iload_2
       8: if_icmpge     40
      11: aload_1
      12: iload         4
      14: iaload
      15: ifge          24
      18: iinc          3, -1
      21: goto          34
      24: aload_1
      25: iload         4
      27: iaload
      28: ifle          34
      31: iinc          3, 1
      34: iinc          4, 1
      37: goto          5
      40: iload_3
      41: ifge          55
      44: getstatic     #5                  // Field java/lang/System.out:Ljava/io/PrintStream;
      47: ldc           #6                  // String neg
      49: invokevirtual #7                  // Method java/io/PrintStream.println:(Ljava/lang/String;)V
      52: goto          78
      55: iload_3
      56: ifle          70
      59: getstatic     #5                  // Field java/lang/System.out:Ljava/io/PrintStream;
      62: ldc           #8                  // String pos
      64: invokevirtual #7                  // Method java/io/PrintStream.println:(Ljava/lang/String;)V
      67: goto          78
      70: getstatic     #5                  // Field java/lang/System.out:Ljava/io/PrintStream;
      73: ldc           #9                  // String bug
      75: invokevirtual #7                  // Method java/io/PrintStream.println:(Ljava/lang/String;)V
      78: return

  public int oneBranch(int);
    descriptor: (I)I
    Code:
       0: iconst_0
       1: istore_2
       2: iload_1
       3: ifge          12
       6: iinc          2, -1
       9: goto          15
      12: iinc          2, 1
      15: iload_2
      16: ireturn
}
