Compiled from "VeritestingPerf.java"
public class VeritestingPerf {
  public VeritestingPerf();
    Code:
       0: aload_0
       1: invokespecial #1                  // Method java/lang/Object."<init>":()V
       4: return

  public static void main(java.lang.String[]);
    Code:
       0: aload_0
       1: iconst_0
       2: aaload
       3: invokestatic  #2                  // Method java/lang/Integer.parseInt:(Ljava/lang/String;)I
       6: istore_1
       7: iload_1
       8: newarray       int
      10: astore_2
      11: new           #3                  // class VeritestingPerf
      14: dup
      15: invokespecial #4                  // Method "<init>":()V
      18: aload_2
      19: iload_1
      20: invokevirtual #5                  // Method testMe4:([II)V
      23: return

  public void testMe4(int[], int);
    Code:
       0: ldc           #6                  // String sum
       2: invokestatic  #7                  // Method gov/nasa/jpf/symbc/Debug.makeSymbolicInteger:(Ljava/lang/String;)I
       5: istore_3
       6: iconst_0
       7: istore        4
       9: iload         4
      11: iload_2
      12: if_icmpge     48
      15: aload_1
      16: iload         4
      18: new           #8                  // class java/lang/StringBuilder
      21: dup
      22: invokespecial #9                  // Method java/lang/StringBuilder."<init>":()V
      25: ldc           #10                 // String x
      27: invokevirtual #11                 // Method java/lang/StringBuilder.append:(Ljava/lang/String;)Ljava/lang/StringBuilder;
      30: iload         4
      32: invokevirtual #12                 // Method java/lang/StringBuilder.append:(I)Ljava/lang/StringBuilder;
      35: invokevirtual #13                 // Method java/lang/StringBuilder.toString:()Ljava/lang/String;
      38: invokestatic  #7                  // Method gov/nasa/jpf/symbc/Debug.makeSymbolicInteger:(Ljava/lang/String;)I
      41: iastore
      42: iinc          4, 1
      45: goto          9
      48: iconst_0
      49: istore        4
      51: iload         4
      53: iload_2
      54: if_icmpge     86
      57: aload_1
      58: iload         4
      60: iaload
      61: ifge          70
      64: iinc          3, -1
      67: goto          80
      70: aload_1
      71: iload         4
      73: iaload
      74: ifle          80
      77: iinc          3, 1
      80: iinc          4, 1
      83: goto          51
      86: iload_3
      87: ifge          101
      90: getstatic     #14                 // Field java/lang/System.out:Ljava/io/PrintStream;
      93: ldc           #15                 // String neg
      95: invokevirtual #16                 // Method java/io/PrintStream.println:(Ljava/lang/String;)V
      98: goto          124
     101: iload_3
     102: ifle          116
     105: getstatic     #14                 // Field java/lang/System.out:Ljava/io/PrintStream;
     108: ldc           #17                 // String pos
     110: invokevirtual #16                 // Method java/io/PrintStream.println:(Ljava/lang/String;)V
     113: goto          124
     116: getstatic     #14                 // Field java/lang/System.out:Ljava/io/PrintStream;
     119: ldc           #18                 // String bug
     121: invokevirtual #16                 // Method java/io/PrintStream.println:(Ljava/lang/String;)V
     124: getstatic     #14                 // Field java/lang/System.out:Ljava/io/PrintStream;
     127: ldc           #19                 // String -x-x-x-x-
     129: invokevirtual #16                 // Method java/io/PrintStream.println:(Ljava/lang/String;)V
     132: return

  public void testMe3(int, int);
    Code:
       0: getstatic     #14                 // Field java/lang/System.out:Ljava/io/PrintStream;
       3: new           #8                  // class java/lang/StringBuilder
       6: dup
       7: invokespecial #9                  // Method java/lang/StringBuilder."<init>":()V
      10: ldc           #20                 // String x =
      12: invokevirtual #11                 // Method java/lang/StringBuilder.append:(Ljava/lang/String;)Ljava/lang/StringBuilder;
      15: iload_1
      16: invokevirtual #12                 // Method java/lang/StringBuilder.append:(I)Ljava/lang/StringBuilder;
      19: ldc           #21                 // String , y =
      21: invokevirtual #11                 // Method java/lang/StringBuilder.append:(Ljava/lang/String;)Ljava/lang/StringBuilder;
      24: iload_2
      25: invokevirtual #12                 // Method java/lang/StringBuilder.append:(I)Ljava/lang/StringBuilder;
      28: invokevirtual #13                 // Method java/lang/StringBuilder.toString:()Ljava/lang/String;
      31: invokevirtual #16                 // Method java/io/PrintStream.println:(Ljava/lang/String;)V
      34: ldc           #22                 // String i
      36: invokestatic  #7                  // Method gov/nasa/jpf/symbc/Debug.makeSymbolicInteger:(Ljava/lang/String;)I
      39: istore_3
      40: bipush        11
      42: istore        4
      44: bipush        12
      46: istore        5
      48: iload_3
      49: iconst_1
      50: if_icmpge     113
      53: iload_1
      54: iload_3
      55: iadd
      56: ifge          65
      59: iconst_m1
      60: istore        4
      62: goto          80
      65: iload_1
      66: iload_3
      67: iadd
      68: ifne          77
      71: iconst_0
      72: istore        4
      74: goto          80
      77: iconst_1
      78: istore        4
      80: iload_2
      81: iload_3
      82: iadd
      83: ifge          92
      86: iconst_m1
      87: istore        5
      89: goto          107
      92: iload_2
      93: iload_3
      94: iadd
      95: ifne          104
      98: iconst_0
      99: istore        5
     101: goto          107
     104: iconst_1
     105: istore        5
     107: iinc          3, 1
     110: goto          48
     113: getstatic     #14                 // Field java/lang/System.out:Ljava/io/PrintStream;
     116: ldc           #19                 // String -x-x-x-x-
     118: invokevirtual #16                 // Method java/io/PrintStream.println:(Ljava/lang/String;)V
     121: return

  public static void testMe(int, boolean);
    Code:
       0: getstatic     #14                 // Field java/lang/System.out:Ljava/io/PrintStream;
       3: new           #8                  // class java/lang/StringBuilder
       6: dup
       7: invokespecial #9                  // Method java/lang/StringBuilder."<init>":()V
      10: ldc           #20                 // String x =
      12: invokevirtual #11                 // Method java/lang/StringBuilder.append:(Ljava/lang/String;)Ljava/lang/StringBuilder;
      15: iload_0
      16: invokevirtual #12                 // Method java/lang/StringBuilder.append:(I)Ljava/lang/StringBuilder;
      19: invokevirtual #13                 // Method java/lang/StringBuilder.toString:()Ljava/lang/String;
      22: invokevirtual #16                 // Method java/io/PrintStream.println:(Ljava/lang/String;)V
      25: iconst_0
      26: istore_2
      27: iload_0
      28: sipush        1200
      31: if_icmpgt     36
      34: iconst_m1
      35: istore_2
      36: iload_0
      37: sipush        1200
      40: if_icmplt     45
      43: iconst_1
      44: istore_2
      45: return

  public void testMe2(int, boolean);
    Code:
       0: getstatic     #14                 // Field java/lang/System.out:Ljava/io/PrintStream;
       3: ldc           #23                 // String !!!!!!!!!!!!!!! First step!
       5: invokevirtual #16                 // Method java/io/PrintStream.println:(Ljava/lang/String;)V
       8: iload_2
       9: ifeq          45
      12: iload_1
      13: sipush        1200
      16: if_icmpgt     27
      19: getstatic     #14                 // Field java/lang/System.out:Ljava/io/PrintStream;
      22: ldc           #24                 // String   <= 1200
      24: invokevirtual #16                 // Method java/io/PrintStream.println:(Ljava/lang/String;)V
      27: iload_1
      28: sipush        1200
      31: if_icmplt     53
      34: getstatic     #14                 // Field java/lang/System.out:Ljava/io/PrintStream;
      37: ldc           #25                 // String   >= 1200
      39: invokevirtual #16                 // Method java/io/PrintStream.println:(Ljava/lang/String;)V
      42: goto          53
      45: getstatic     #14                 // Field java/lang/System.out:Ljava/io/PrintStream;
      48: ldc           #26                 // String   b is false
      50: invokevirtual #16                 // Method java/io/PrintStream.println:(Ljava/lang/String;)V
      53: return
}
